kerops/__init__.py
kerops/__version__.py
kerops/utils.py
kerops/kernels/__init__.py
kerops/kernels/addition.py
kerops/kernels/avgpool.py
kerops/kernels/bnrelu.py
kerops/kernels/dw_conv.py
kerops/kernels/linear.py
kerops/kernels/quantization.py
kerops/kernels/stats.py
kerops/ops/__init__.py
kerops/ops/addition.py
kerops/ops/avgpool.py
kerops/ops/bnrelu.py
kerops/ops/quantization.py
kerops/ops/stats.py
kerops/ops/conv/__init__.py
kerops/ops/conv/dwconv.py
kerops/ops/conv/dwconv_wgrad.py
kerops/ops/linear/__init__.py
kerops/ops/linear/linear_bias_relu_linear_add.py
kerops/ops/linear/linear_bias_relu_linear_backward.py
kerops/ops/linear/relu_linear_add.py
kerops/ops/linear/relu_linear_backward.py
kerops/settings/__init__.py
kerops/settings/hardware_conf.py
kerops/settings/utils.py
kerops/settings/wrapper.py
tests/conftest.py
tests/ops/test_add.py
tests/ops/test_avgpool.py
tests/ops/test_bn_relu.py
tests/ops/test_conv.py
tests/ops/test_linear.py
tests/ops/test_stats.py
kerops-0.0.5.dist-info/LICENSE
kerops-0.0.5.dist-info/METADATA
kerops-0.0.5.dist-info/WHEEL
kerops-0.0.5.dist-info/top_level.txt
kerops-0.0.5.dist-info/RECORD
