Metadata-Version: 2.2
Name: kerops
Version: 0.0.5
Summary: Efficient gpu algorithms for 3D computer vision
Author-email: AnihilatorGun <nikitaushakov.nu35@gmail.com>
License: MIT License
Project-URL: Homepage, https://github.com/neuro-ml/kerops
Project-URL: Issues, https://github.com/neuro-ml/kerops/issues
Project-URL: Source, https://github.com/neuro-ml/kerops
Keywords: computer vision,fast,gpu,triton
Classifier: Development Status :: 4 - Beta
Classifier: License :: OSI Approved :: MIT License
Classifier: Programming Language :: Python :: 3.10
Classifier: Programming Language :: Python :: 3.11
Classifier: Programming Language :: Python :: 3.12
Requires-Python: >=3.10
License-File: LICENSE
Requires-Dist: triton==3.1.0
Requires-Dist: torch
